dgpost/__init__.py
dgpost/main.py
dgpost/transform/__init__.py
dgpost/transform/catalysis.py
dgpost/transform/chromatography.py
dgpost/transform/complex.py
dgpost/transform/electrochemistry.py
dgpost/transform/impedance.py
dgpost/transform/mixtures.py
dgpost/transform/rates.py
dgpost/transform/reflection.py
dgpost/transform/table.py
dgpost/transform/circuit_utils/__init__.py
dgpost/transform/circuit_utils/circuit_components.py
dgpost/transform/circuit_utils/circuit_parser.py
dgpost/utils/__init__.py
dgpost/utils/extract.py
dgpost/utils/helpers.py
dgpost/utils/load.py
dgpost/utils/parse.py
dgpost/utils/pivot.py
dgpost/utils/plot.py
dgpost/utils/save.py
dgpost/utils/transform.py
dgpost-2.3.dist-info/licenses/LICENSE
dgpost-2.3.dist-info/METADATA
dgpost-2.3.dist-info/WHEEL
dgpost-2.3.dist-info/entry_points.txt
dgpost-2.3.dist-info/top_level.txt
dgpost-2.3.dist-info/RECORD
