Metadata-Version: 2.4
Name: dgpost
Version: 2.3
Summary: datagram post-processing toolkit
Author: Ueli Sauter
Author-email: Peter Kraus <peter.kraus@tu-berlin.de>
Maintainer-email: Peter Kraus <peter.kraus@tu-berlin.de>
Project-URL: Documentation, https://dgbowl.github.io/dgpost/master
Project-URL: Issues, https://github.com/dgbowl/dgpost/issues
Project-URL: Repository, https://github.com/dgbowl/dgpost/
Classifier: Development Status :: 5 - Production/Stable
Classifier: License :: OSI Approved :: GNU General Public License v3 or later (GPLv3+)
Classifier: Programming Language :: Python :: 3.10
Classifier: Programming Language :: Python :: 3.11
Classifier: Programming Language :: Python :: 3.12
Classifier: Programming Language :: Python :: 3.13
Classifier: Operating System :: OS Independent
Requires-Python: >=3.10
License-File: LICENSE
Requires-Dist: numpy>=1.20
Requires-Dist: uncertainties<3.2
Requires-Dist: pandas
Requires-Dist: openpyxl
Requires-Dist: pint>=0.24.1
Requires-Dist: chemicals>=1.0.0
Requires-Dist: rdkit>=2022.3
Requires-Dist: h5netcdf>=1.0
Requires-Dist: xarray>=2024.10.0
Requires-Dist: dgbowl-schemas>=122
Requires-Dist: matplotlib>=3.5.0
Provides-Extra: testing
Requires-Dist: pytest; extra == "testing"
Requires-Dist: ruff; extra == "testing"
Provides-Extra: docs
Requires-Dist: sphinx~=7.2; extra == "docs"
Requires-Dist: sphinx-rtd-theme~=1.3.0; extra == "docs"
Requires-Dist: autodoc-pydantic~=2.1.0; extra == "docs"
Dynamic: license-file
